Metadata-Version: 2.1
Name: TensorFlow1
Version: 3.2.0
Summary: TensorFlow1, Effortless Dataset Extraction
Author: Ibrahim
Author-email: string2025@gmail.com
License-File: license
